fileprompt/__init__.py
fileprompt/cli.py
fileprompt/fs.py
fileprompt/main.py
fileprompt/models.py
fileprompt/payload.py
fileprompt/watcher.py
fileprompt/templates/index.html
fileprompt-0.1.0.dist-info/METADATA
fileprompt-0.1.0.dist-info/WHEEL
fileprompt-0.1.0.dist-info/entry_points.txt
fileprompt-0.1.0.dist-info/top_level.txt
fileprompt-0.1.0.dist-info/RECORD
