Metadata-Version: 2.4
Name: fileprompt
Version: 0.1.0
Summary: Turn any local codebase into an LLM-ready prompt.
Requires-Python: >=3.11
Requires-Dist: fastapi==0.111.0
Requires-Dist: uvicorn[standard]
Requires-Dist: watchdog
Requires-Dist: tiktoken
Requires-Dist: jinja2
Provides-Extra: dev
Requires-Dist: pytest; extra == "dev"
Requires-Dist: pytest-asyncio; extra == "dev"
